SPICE/Melange.py
SPICE/Soma.py
SPICE/__init__.py
spice_bio-1.0.1.dist-info/LICENSE
spice_bio-1.0.1.dist-info/METADATA
spice_bio-1.0.1.dist-info/WHEEL
spice_bio-1.0.1.dist-info/top_level.txt
spice_bio-1.0.1.dist-info/RECORD
