Metadata-Version: 2.1
Name: spice-bio
Version: 1.0.1
Summary: Generative Design of Cell Type-Specific mRNA Splicing Elements for Programmable Gene Regulation
Home-page: https://github.com/caokai1073/SPICE
Author: Kai Cao
Author-email: caokai1073@gmail.com
License: UNKNOWN
Platform: UNKNOWN
Classifier: Programming Language :: Python :: 3
Classifier: Programming Language :: Python :: 3.9
Classifier: Programming Language :: Python :: 3.10
Classifier: Programming Language :: Python :: 3.11
Classifier: License :: OSI Approved :: MIT License
Classifier: Operating System :: OS Independent
Requires-Python: >=3.9
License-File: LICENSE
Requires-Dist: numpy
Requires-Dist: pandas
Requires-Dist: torch
Requires-Dist: scikit-learn
Requires-Dist: tqdm
Requires-Dist: transformers
Requires-Dist: matplotlib
Requires-Dist: scipy
